chatgpt_interface/__init__.py
chatgpt_interface/chatgpt_interface.py
chatgpt_interface-0.1.7.dist-info/METADATA
chatgpt_interface-0.1.7.dist-info/WHEEL
chatgpt_interface-0.1.7.dist-info/top_level.txt
chatgpt_interface-0.1.7.dist-info/RECORD
